{
    "codeToName": {
        "0": ".null",
        "8": ".null",
        "9": "CR",
        "13": "CR",
        "29": ".null",
        "32": "space",
        "33": "exclam",
        "34": "quotedbl",
        "35": "numbersign",
        "36": "dollar",
        "37": "percent",
        "38": "ampersand",
        "39": "quotesingle",
        "40": "parenleft",
        "41": "parenright",
        "42": "asterisk",
        "43": "plus",
        "44": "comma",
        "45": "hyphen",
        "46": "period",
        "47": "slash",
        "48": "zero",
        "49": "one",
        "50": "two",
        "51": "three",
        "52": "four",
        "53": "five",
        "54": "six",
        "55": "seven",
        "56": "eight",
        "57": "nine",
        "58": "colon",
        "59": "semicolon",
        "60": "less",
        "61": "equal",
        "62": "greater",
        "63": "question",
        "64": "at",
        "65": "A",
        "66": "B",
        "67": "C",
        "68": "D",
        "69": "E",
        "70": "F",
        "71": "G",
        "72": "H",
        "73": "I",
        "74": "J",
        "75": "K",
        "76": "L",
        "77": "M",
        "78": "N",
        "79": "O",
        "80": "P",
        "81": "Q",
        "82": "R",
        "83": "S",
        "84": "T",
        "85": "U",
        "86": "V",
        "87": "W",
        "88": "X",
        "89": "Y",
        "90": "Z",
        "91": "bracketleft",
        "92": "backslash",
        "93": "bracketright",
        "94": "asciicircum",
        "95": "underscore",
        "96": "grave",
        "97": "a",
        "98": "b",
        "99": "c",
        "100": "d",
        "101": "e",
        "102": "f",
        "103": "g",
        "104": "h",
        "105": "i",
        "106": "j",
        "107": "k",
        "108": "l",
        "109": "m",
        "110": "n",
        "111": "o",
        "112": "p",
        "113": "q",
        "114": "r",
        "115": "s",
        "116": "t",
        "117": "u",
        "118": "v",
        "119": "w",
        "120": "x",
        "121": "y",
        "122": "z",
        "123": "braceleft",
        "124": "bar",
        "125": "braceright",
        "126": "asciitilde",
        "160": "uni00A0",
        "161": "exclamdown",
        "162": "cent",
        "163": "sterling",
        "164": "currency",
        "165": "yen",
        "166": "brokenbar",
        "167": "section",
        "168": "dieresis",
        "169": "copyright",
        "170": "ordfeminine",
        "171": "guillemotleft",
        "172": "logicalnot",
        "173": "uni00AD",
        "174": "registered",
        "175": "macron",
        "176": "degree",
        "177": "plusminus",
        "178": "twosuperior",
        "179": "threesuperior",
        "180": "acute",
        "181": "mu",
        "182": "paragraph",
        "183": "periodcentered",
        "184": "cedilla",
        "185": "onesuperior",
        "186": "ordmasculine",
        "187": "guillemotright",
        "188": "onequarter",
        "189": "onehalf",
        "190": "threequarters",
        "191": "questiondown",
        "192": "Agrave",
        "193": "Aacute",
        "194": "Acircumflex",
        "195": "Atilde",
        "196": "Adieresis",
        "197": "Aring",
        "198": "AE",
        "199": "Ccedilla",
        "200": "Egrave",
        "201": "Eacute",
        "202": "Ecircumflex",
        "203": "Edieresis",
        "204": "Igrave",
        "205": "Iacute",
        "206": "Icircumflex",
        "207": "Idieresis",
        "208": "Eth",
        "209": "Ntilde",
        "210": "Ograve",
        "211": "Oacute",
        "212": "Ocircumflex",
        "213": "Otilde",
        "214": "Odieresis",
        "215": "multiply",
        "216": "Oslash",
        "217": "Ugrave",
        "218": "Uacute",
        "219": "Ucircumflex",
        "220": "Udieresis",
        "221": "Yacute",
        "222": "Thorn",
        "223": "germandbls",
        "224": "agrave",
        "225": "aacute",
        "226": "acircumflex",
        "227": "atilde",
        "228": "adieresis",
        "229": "aring",
        "230": "ae",
        "231": "ccedilla",
        "232": "egrave",
        "233": "eacute",
        "234": "ecircumflex",
        "235": "edieresis",
        "236": "igrave",
        "237": "iacute",
        "238": "icircumflex",
        "239": "idieresis",
        "240": "eth",
        "241": "ntilde",
        "242": "ograve",
        "243": "oacute",
        "244": "ocircumflex",
        "245": "otilde",
        "246": "odieresis",
        "247": "divide",
        "248": "oslash",
        "249": "ugrave",
        "250": "uacute",
        "251": "ucircumflex",
        "252": "udieresis",
        "253": "yacute",
        "254": "thorn",
        "255": "ydieresis",
        "256": "Amacron",
        "257": "amacron",
        "258": "Abreve",
        "259": "abreve",
        "260": "Aogonek",
        "261": "aogonek",
        "262": "Cacute",
        "263": "cacute",
        "264": "Ccircumflex",
        "265": "ccircumflex",
        "266": "Cdotaccent",
        "267": "cdotaccent",
        "268": "Ccaron",
        "269": "ccaron",
        "270": "Dcaron",
        "271": "dcaron",
        "272": "Dcroat",
        "273": "dmacron",
        "274": "Emacron",
        "275": "emacron",
        "276": "Ebreve",
        "277": "ebreve",
        "278": "Edotaccent",
        "279": "edotaccent",
        "280": "Eogonek",
        "281": "eogonek",
        "282": "Ecaron",
        "283": "ecaron",
        "284": "Gcircumflex",
        "285": "gcircumflex",
        "286": "Gbreve",
        "287": "gbreve",
        "288": "Gdotaccent",
        "289": "gdotaccent",
        "290": "Gcommaaccent",
        "291": "gcommaaccent",
        "292": "Hcircumflex",
        "293": "hcircumflex",
        "294": "Hbar",
        "295": "hbar",
        "296": "Itilde",
        "297": "itilde",
        "298": "Imacron",
        "299": "imacron",
        "300": "Ibreve",
        "301": "ibreve",
        "302": "Iogonek",
        "303": "iogonek",
        "304": "Idot",
        "305": "dotlessi",
        "306": "IJ",
        "307": "ij",
        "308": "Jcircumflex",
        "309": "jcircumflex",
        "310": "Kcommaaccent",
        "311": "kcommaaccent",
        "312": "kgreenlandic",
        "313": "Lacute",
        "314": "lacute",
        "315": "Lcommaaccent",
        "316": "lcommaaccent",
        "317": "Lcaron",
        "318": "lcaron",
        "319": "Ldot",
        "320": "ldot",
        "321": "Lslash",
        "322": "lslash",
        "323": "Nacute",
        "324": "nacute",
        "325": "Ncommaaccent",
        "326": "ncommaaccent",
        "327": "Ncaron",
        "328": "ncaron",
        "329": "napostrophe",
        "330": "Eng",
        "331": "eng",
        "332": "Omacron",
        "333": "omacron",
        "334": "Obreve",
        "335": "obreve",
        "336": "Ohungarumlaut",
        "337": "ohungarumlaut",
        "338": "OE",
        "339": "oe",
        "340": "Racute",
        "341": "racute",
        "342": "Rcommaaccent",
        "343": "rcommaaccent",
        "344": "Rcaron",
        "345": "rcaron",
        "346": "Sacute",
        "347": "sacute",
        "348": "Scircumflex",
        "349": "scircumflex",
        "350": "Scedilla",
        "351": "scedilla",
        "352": "Scaron",
        "353": "scaron",
        "354": "uni0162",
        "355": "uni0163",
        "356": "Tcaron",
        "357": "tcaron",
        "358": "Tbar",
        "359": "tbar",
        "360": "Utilde",
        "361": "utilde",
        "362": "Umacron",
        "363": "umacron",
        "364": "Ubreve",
        "365": "ubreve",
        "366": "Uring",
        "367": "uring",
        "368": "Uhungarumlaut",
        "369": "uhungarumlaut",
        "370": "Uogonek",
        "371": "uogonek",
        "372": "Wcircumflex",
        "373": "wcircumflex",
        "374": "Ycircumflex",
        "375": "ycircumflex",
        "376": "Ydieresis",
        "377": "Zacute",
        "378": "zacute",
        "379": "Zdotaccent",
        "380": "zdotaccent",
        "381": "Zcaron",
        "382": "zcaron",
        "383": "longs",
        "402": "florin",
        "536": "Scommaaccent",
        "537": "scommaaccent",
        "538": "uni021A",
        "539": "uni021B",
        "567": "dotlessj",
        "700": "apostrophe",
        "710": "circumflex",
        "711": "caron",
        "713": "uni02C9",
        "728": "breve",
        "729": "dotaccent",
        "730": "ring",
        "731": "ogonek",
        "732": "tilde",
        "733": "hungarumlaut",
        "916": "uni0394",
        "937": "Omega",
        "956": "uni03BC",
        "960": "pi",
        "7808": "Wgrave",
        "7809": "wgrave",
        "7810": "Wacute",
        "7811": "wacute",
        "7812": "Wdieresis",
        "7813": "wdieresis",
        "7922": "Ygrave",
        "7923": "ygrave",
        "8211": "endash",
        "8212": "emdash",
        "8216": "quoteleft",
        "8217": "quoteright",
        "8218": "quotesinglbase",
        "8220": "quotedblleft",
        "8221": "quotedblright",
        "8222": "quotedblbase",
        "8224": "dagger",
        "8225": "daggerdbl",
        "8226": "bullet",
        "8230": "ellipsis",
        "8240": "perthousand",
        "8249": "guilsinglleft",
        "8250": "guilsinglright",
        "8260": "fraction",
        "8304": "zerosuperior",
        "8308": "foursuperior",
        "8309": "fivesuperior",
        "8310": "sixsuperior",
        "8311": "sevensuperior",
        "8312": "eightsuperior",
        "8313": "ninesuperior",
        "8320": "zeroinferior",
        "8321": "oneinferior",
        "8322": "twoinferior",
        "8323": "threeinferior",
        "8324": "fourinferior",
        "8325": "fiveinferior",
        "8326": "sixinferior",
        "8327": "seveninferior",
        "8328": "eightinferior",
        "8329": "nineinferior",
        "8364": "Euro",
        "8377": "uni20B9",
        "8378": "uni20BA",
        "8467": "afii61289",
        "8482": "trademark",
        "8486": "uni2126",
        "8494": "estimated",
        "8531": "onethird",
        "8532": "twothirds",
        "8533": "onefifth",
        "8534": "twofifths",
        "8535": "threefifths",
        "8536": "fourfifths",
        "8537": "onesixth",
        "8538": "fivesixths",
        "8539": "oneeighth",
        "8540": "threeeighths",
        "8541": "fiveeighths",
        "8542": "seveneighths",
        "8706": "partialdiff",
        "8710": "increment",
        "8719": "product",
        "8721": "summation",
        "8722": "minus",
        "8725": "uni2215",
        "8729": "uni2219",
        "8730": "radical",
        "8734": "infinity",
        "8747": "integral",
        "8776": "approxequal",
        "8800": "notequal",
        "8804": "lessequal",
        "8805": "greaterequal",
        "9674": "lozenge",
        "61441": "fi",
        "61442": "fl",
        "62726": "oneseventh",
        "62727": "twosevenths",
        "62728": "threesevenths",
        "62729": "foursevenths",
        "62730": "fivesevenths",
        "62731": "sixsevenths",
        "62732": "oneninth",
        "62733": "twoninths",
        "62734": "fourninths",
        "62735": "fiveninths",
        "62736": "sevenninths",
        "62737": "eightninths",
        "63488": "zero.alt",
        "63489": "one.alt",
        "63490": "two.alt",
        "63491": "three.alt",
        "63492": "four.alt",
        "63493": "five.alt",
        "63494": "six.alt",
        "63495": "seven.alt",
        "63496": "eight.alt",
        "63497": "nine.alt",
        "63498": "zero.sups",
        "63499": "one.sups",
        "63500": "two.sups",
        "63501": "three.sups",
        "63502": "four.sups",
        "63503": "five.sups",
        "63504": "six.sups",
        "63505": "seven.sups",
        "63506": "eight.sups",
        "63507": "nine.sups",
        "63508": "zero.sinf",
        "63509": "one.sinf",
        "63510": "two.sinf",
        "63511": "three.sinf",
        "63512": "four.sinf",
        "63513": "five.sinf",
        "63514": "six.sinf",
        "63515": "seven.sinf",
        "63516": "eight.sinf",
        "63517": "nine.sinf",
        "64256": "f_f",
        "64257": "f_i",
        "64258": "f_l",
        "64259": "f_f_i",
        "64260": "f_f_l"
    },
    "isUnicode": true,
    "EncodingScheme": "FontSpecific",
    "FontName": "AktivGrotesk-Black",
    "FullName": "\u261eAktiv Grotesk Black",
    "Version": "Version 1.013;com.myfonts.easy.daltonmaag.aktiv-grotesk.black.wfkit2.version.4cyo",
    "PostScriptName": "AktivGrotesk-Black",
    "Weight": "Medium",
    "ItalicAngle": "0",
    "IsFixedPitch": "false",
    "UnderlineThickness": "68",
    "UnderlinePosition": "-99",
    "FontHeightOffset": "252",
    "Ascender": "779",
    "Descender": "-221",
    "FontBBox": [
        "-175",
        "-243",
        "1413",
        "1009"
    ],
    "StartCharMetrics": "504",
    "C": {
        "0": 0,
        "8": 0,
        "9": 210,
        "13": 210,
        "29": 0,
        "32": 210,
        "33": 335,
        "34": 486,
        "35": 592,
        "36": 592,
        "37": 1024,
        "38": 729,
        "39": 251,
        "40": 379,
        "41": 379,
        "42": 441,
        "43": 592,
        "44": 288,
        "45": 427,
        "46": 288,
        "47": 464,
        "48": 592,
        "49": 592,
        "50": 592,
        "51": 592,
        "52": 592,
        "53": 592,
        "54": 592,
        "55": 592,
        "56": 592,
        "57": 592,
        "58": 288,
        "59": 288,
        "60": 592,
        "61": 592,
        "62": 592,
        "63": 558,
        "64": 1030,
        "65": 782,
        "66": 693,
        "67": 738,
        "68": 765,
        "69": 636,
        "70": 601,
        "71": 770,
        "72": 764,
        "73": 347,
        "74": 687,
        "75": 749,
        "76": 606,
        "77": 903,
        "78": 755,
        "79": 800,
        "80": 666,
        "81": 800,
        "82": 704,
        "83": 691,
        "84": 675,
        "85": 738,
        "86": 758,
        "87": 1029,
        "88": 758,
        "89": 716,
        "90": 656,
        "91": 420,
        "92": 464,
        "93": 420,
        "94": 592,
        "95": 500,
        "96": 445,
        "97": 599,
        "98": 642,
        "99": 581,
        "100": 642,
        "101": 605,
        "102": 438,
        "103": 642,
        "104": 626,
        "105": 314,
        "106": 319,
        "107": 646,
        "108": 314,
        "109": 903,
        "110": 626,
        "111": 627,
        "112": 642,
        "113": 642,
        "114": 462,
        "115": 559,
        "116": 459,
        "117": 621,
        "118": 604,
        "119": 835,
        "120": 605,
        "121": 616,
        "122": 541,
        "123": 431,
        "124": 322,
        "125": 431,
        "126": 592,
        "160": 210,
        "161": 315,
        "162": 592,
        "163": 592,
        "164": 592,
        "165": 592,
        "166": 322,
        "167": 601,
        "168": 445,
        "169": 782,
        "170": 443,
        "171": 664,
        "172": 592,
        "173": 427,
        "174": 508,
        "175": 445,
        "176": 398,
        "177": 592,
        "178": 412,
        "179": 412,
        "180": 445,
        "181": 626,
        "182": 732,
        "183": 288,
        "184": 445,
        "185": 412,
        "186": 455,
        "187": 664,
        "188": 1053,
        "189": 1053,
        "190": 1053,
        "191": 538,
        "192": 782,
        "193": 782,
        "194": 782,
        "195": 782,
        "196": 782,
        "197": 782,
        "198": 1097,
        "199": 738,
        "200": 636,
        "201": 636,
        "202": 636,
        "203": 636,
        "204": 347,
        "205": 347,
        "206": 347,
        "207": 347,
        "208": 796,
        "209": 755,
        "210": 800,
        "211": 800,
        "212": 800,
        "213": 800,
        "214": 800,
        "215": 592,
        "216": 800,
        "217": 738,
        "218": 738,
        "219": 738,
        "220": 738,
        "221": 716,
        "222": 659,
        "223": 658,
        "224": 599,
        "225": 599,
        "226": 599,
        "227": 599,
        "228": 599,
        "229": 599,
        "230": 903,
        "231": 581,
        "232": 605,
        "233": 605,
        "234": 605,
        "235": 605,
        "236": 314,
        "237": 314,
        "238": 314,
        "239": 314,
        "240": 631,
        "241": 626,
        "242": 627,
        "243": 627,
        "244": 627,
        "245": 627,
        "246": 627,
        "247": 592,
        "248": 627,
        "249": 621,
        "250": 621,
        "251": 621,
        "252": 621,
        "253": 616,
        "254": 642,
        "255": 616,
        "256": 782,
        "257": 599,
        "258": 782,
        "259": 599,
        "260": 782,
        "261": 599,
        "262": 738,
        "263": 581,
        "264": 738,
        "265": 581,
        "266": 738,
        "267": 581,
        "268": 738,
        "269": 581,
        "270": 760,
        "271": 641,
        "272": 796,
        "273": 642,
        "274": 636,
        "275": 605,
        "276": 636,
        "277": 605,
        "278": 636,
        "279": 605,
        "280": 636,
        "281": 605,
        "282": 636,
        "283": 605,
        "284": 770,
        "285": 642,
        "286": 770,
        "287": 642,
        "288": 770,
        "289": 642,
        "290": 770,
        "291": 642,
        "292": 764,
        "293": 626,
        "294": 826,
        "295": 626,
        "296": 347,
        "297": 314,
        "298": 347,
        "299": 314,
        "300": 347,
        "301": 314,
        "302": 347,
        "303": 314,
        "304": 347,
        "305": 314,
        "306": 1034,
        "307": 633,
        "308": 687,
        "309": 319,
        "310": 749,
        "311": 646,
        "312": 646,
        "313": 606,
        "314": 314,
        "315": 606,
        "316": 314,
        "317": 616,
        "318": 312,
        "319": 616,
        "320": 555,
        "321": 636,
        "322": 424,
        "323": 755,
        "324": 626,
        "325": 755,
        "326": 626,
        "327": 755,
        "328": 626,
        "329": 831,
        "330": 755,
        "331": 626,
        "332": 800,
        "333": 627,
        "334": 800,
        "335": 627,
        "336": 800,
        "337": 627,
        "338": 1056,
        "339": 932,
        "340": 704,
        "341": 462,
        "342": 704,
        "343": 462,
        "344": 704,
        "345": 462,
        "346": 691,
        "347": 559,
        "348": 691,
        "349": 559,
        "350": 691,
        "351": 559,
        "352": 691,
        "353": 559,
        "354": 675,
        "355": 459,
        "356": 675,
        "357": 459,
        "358": 675,
        "359": 484,
        "360": 738,
        "361": 621,
        "362": 738,
        "363": 621,
        "364": 738,
        "365": 621,
        "366": 738,
        "367": 621,
        "368": 738,
        "369": 621,
        "370": 738,
        "371": 621,
        "372": 1029,
        "373": 835,
        "374": 716,
        "375": 616,
        "376": 716,
        "377": 656,
        "378": 541,
        "379": 656,
        "380": 541,
        "381": 656,
        "382": 541,
        "383": 324,
        "402": 438,
        "536": 691,
        "537": 559,
        "538": 675,
        "539": 459,
        "567": 319,
        "700": 445,
        "710": 445,
        "711": 445,
        "713": 445,
        "728": 445,
        "729": 445,
        "730": 445,
        "731": 445,
        "732": 445,
        "733": 445,
        "916": 762,
        "937": 803,
        "956": 626,
        "960": 711,
        "7808": 1029,
        "7809": 835,
        "7810": 1029,
        "7811": 835,
        "7812": 1029,
        "7813": 835,
        "7922": 716,
        "7923": 616,
        "8211": 500,
        "8212": 1000,
        "8216": 288,
        "8217": 288,
        "8218": 288,
        "8220": 534,
        "8221": 534,
        "8222": 534,
        "8224": 528,
        "8225": 548,
        "8226": 416,
        "8230": 1097,
        "8240": 1097,
        "8249": 389,
        "8250": 389,
        "8260": 149,
        "8304": 412,
        "8308": 412,
        "8309": 412,
        "8310": 412,
        "8311": 412,
        "8312": 412,
        "8313": 412,
        "8320": 412,
        "8321": 412,
        "8322": 412,
        "8323": 412,
        "8324": 412,
        "8325": 412,
        "8326": 412,
        "8327": 412,
        "8328": 412,
        "8329": 412,
        "8364": 592,
        "8377": 592,
        "8378": 592,
        "8467": 574,
        "8482": 967,
        "8486": 803,
        "8494": 911,
        "8531": 1053,
        "8532": 1053,
        "8533": 1053,
        "8534": 1053,
        "8535": 1053,
        "8536": 1053,
        "8537": 1053,
        "8538": 1053,
        "8539": 1053,
        "8540": 1053,
        "8541": 1053,
        "8542": 1053,
        "8706": 608,
        "8710": 762,
        "8719": 760,
        "8721": 651,
        "8722": 592,
        "8725": 149,
        "8729": 288,
        "8730": 682,
        "8734": 600,
        "8747": 396,
        "8776": 592,
        "8800": 592,
        "8804": 592,
        "8805": 592,
        "9674": 652,
        "61441": 769,
        "61442": 767,
        "62726": 1053,
        "62727": 1053,
        "62728": 1053,
        "62729": 1053,
        "62730": 1053,
        "62731": 1053,
        "62732": 1053,
        "62733": 1053,
        "62734": 1053,
        "62735": 1053,
        "62736": 1053,
        "62737": 1053,
        "63488": 627,
        "63489": 477,
        "63490": 607,
        "63491": 600,
        "63492": 616,
        "63493": 578,
        "63494": 601,
        "63495": 587,
        "63496": 612,
        "63497": 601,
        "63498": 412,
        "63499": 412,
        "63500": 412,
        "63501": 412,
        "63502": 412,
        "63503": 412,
        "63504": 412,
        "63505": 412,
        "63506": 412,
        "63507": 412,
        "63508": 412,
        "63509": 412,
        "63510": 412,
        "63511": 412,
        "63512": 412,
        "63513": 412,
        "63514": 412,
        "63515": 412,
        "63516": 412,
        "63517": 412,
        "64256": 901,
        "64257": 769,
        "64258": 767,
        "64259": 1097,
        "64260": 1097
    },
    "CIDtoGID_Compressed": true,
    "CIDtoGID": "eJzt0mOwZVcUhdE527Zt27Zt27Zt27Zt20Zs27a6kvsjnUY6r17npTvfqDp37dprY546V9btrFCBUSjd3x87QyuMwiqcwiuCIiqSIiuKoiqaoiuGYiqWYiuO4iqe4iuBEiqREiuJkiqZkiuFUiqVUiuN0iqd0iuDMiqTMiuLsiqbsiuHciqXciuP8iqf8quACqqQCquIiqqYiquESqqUSquMyqqcyquCKqqSKquKqqqaqquGaqqWaquO6qqe6quBGqqRGquJmqqZmquFWv7NGz6IVmqtNmqrdmqvDuqoTuqsLuqqbuquHuqpXuqtPuqrfuqvARqoQRqsIRqqYRquERqpURqtMRqrcRqvCZqoSZqsKZqqaZquGZqpWZqtOZqreZqvBVqoRVqsJVqqZVquFVqpVVqtNVqrdVqvDdqoTdqsLdqqbdquHdqpXdqtPdqrfdqvAzqoQzqsIzqqYzquEzqpUzqtMzqrczqvC7qoS7qsK7qqa7quG7qpJ\/SkntLTekbP6jk9rxf0ol7Sy3pFr+o1va439Kbe0tt6R+\/qPb2vD\/ShPtLH+kSf6jN9ri\/0pb7S1\/pG3+o7fa8f9KN+0s\/6Rb9atkM5tMM4rMM5vCM4oiM5sqM4qqM5umM4pmM5tuM4ruM5vhM4oRM5sZM4qZM5uVM4pVM5tdM4rdM5vTM4ozM5s7M4q7M5u3M4p3M5t\/M4r\/M5vwu4oAu5sIu4qIu5uEu45IN8YpcKhv\/JY8KlXcZlXS6Iu8sHb5pHlyvcZa6iK936rXzffVVc1dVc3TVc82Flw51c64FX1n6gVXUCtW7Q8gAAAAAAAAAAAAAAAAAAAAAAAADA4871XN8N3NCN3DikszwsbuKmIZ0BjzI3c\/PAqIVbutWt2tpt3PZWbef27hDodbzLzk53zHR2l7us6xqcef90brdA7e4e7ule7u0+t\/X7up\/7e4AHepAHe4iHeliw3Dv8np0RHhkcN\/ybPOq+3dGBOuYv82OD7f5xHu8JnuhJnuwpnuppnu4Znhlc5\/+\/eVagzr6jM+fWM9fzfh\/PD8wt8MLAaNE9T1wc5CxL\/uH6pYG6zMuDeicAAP8FXhHSCQAAAAAAAAAAAAAAAAAAAAAAAAAAAAAAAAAAAAAAAAAAAAAAAAAAAAAAAAAAAAAAAAAAAAAAAAAAAAAAAAAAAAAAAAAAAAAAAAAAAAAAAAAAAAAAAAAAAAAAAAAAAAAAAAAAAAAAAAAAAAAAAAAAAAAAAAAAAAAAAAAAAAAAAAAAAAAAAAAAAAAAAAAAAAAAAAAAAAAAAB4nXulVIZ0BAAAAIcGrvcZrvc7rvcEbvcmbvcVbvS2kcwEAgp+3e4d3epd3e4\/3ep\/3+4AP+pAP+4iP+piP+4RP+pRP+4zP+pzP+4Iv+pIv+0pIZwcABJ2v+pqv+4ZvhnQSAAAA\/Bt+AwGN1hA=",
    "_version_": 6
}